{
  "qq_number": "2801958920",
  "group_number": "532982847",
  "updated_at": "2026-04-23T15:52:38.331166",
  "skins": [
    {
      "name": "水の草莓电波",
      "file": "水の草莓电波脆.bdi",
      "thumb": "水の草莓电波脆.bdi_py_26_light_thumb.png",
      "full": "水の草莓电波脆.bdi_py_26_light.png"
    },
    {
      "name": "水の草莓电波",
      "file": "水の草莓电波.bdi",
      "thumb": "水の草莓电波.bdi_py_26_light_thumb.png",
      "full": "水の草莓电波.bdi_py_26_light.png"
    },
    {
      "name": "乐妍贴纸底包1",
      "file": "水のY2K甜酷辣妹闷.bdi",
      "thumb": "水のY2K甜酷辣妹闷.bdi_py_26_light_thumb.png",
      "full": "水のY2K甜酷辣妹闷.bdi_py_26_light.png"
    },
    {
      "name": "乐妍贴纸底包1",
      "file": "水のY2K甜酷辣妹.bdi",
      "thumb": "水のY2K甜酷辣妹.bdi_py_26_light_thumb.png",
      "full": "水のY2K甜酷辣妹.bdi_py_26_light.png"
    },
    {
      "name": "水の草莓电波",
      "file": "水の草莓电波彩底.bds",
      "thumb": "水の草莓电波彩底.bds_py_26_light_thumb.png",
      "full": "水の草莓电波彩底.bds_py_26_light.png"
    },
    {
      "name": "水のY2K甜酷辣妹",
      "file": "水のY2K甜酷辣妹彩底.bds",
      "thumb": "水のY2K甜酷辣妹彩底.bds_py_26_light_thumb.png",
      "full": "水のY2K甜酷辣妹彩底.bds_py_26_light.png"
    },
    {
      "name": "水のY2K甜酷辣妹",
      "file": "水のY2K甜酷辣妹彩底闷.bds",
      "thumb": "水のY2K甜酷辣妹彩底闷.bds_py_26_light_thumb.png",
      "full": "水のY2K甜酷辣妹彩底闷.bds_py_26_light.png"
    },
    {
      "name": "水の草莓电波",
      "file": "水の草莓电波彩底脆.bds",
      "thumb": "水の草莓电波彩底脆.bds_py_26_light_thumb.png",
      "full": "水の草莓电波彩底脆.bds_py_26_light.png"
    }
  ]
}